run_mltrace.py
cloud_diagnostics_xprof/__init__.py
cloud_diagnostics_xprof/data_generator.py
cloud_diagnostics_xprof/xprof.py
cloud_diagnostics_xprof/actions/action.py
cloud_diagnostics_xprof/actions/capture_action.py
cloud_diagnostics_xprof/actions/connect_action.py
cloud_diagnostics_xprof/actions/create_action.py
cloud_diagnostics_xprof/actions/delete_action.py
cloud_diagnostics_xprof/actions/list_action.py
cloud_diagnostics_xprof/actions/register_action.py
cloud_diagnostics_xprof-0.1.1.dist-info/licenses/LICENSE
mltrace/__init__.py
mltrace/constants.py
mltrace/log_parser.py
mltrace/main.py
mltrace/option_parser.py
mltrace/perfetto_trace_utils.py
mltrace/log_reader/__init__.py
mltrace/log_reader/cloud_logging_log_reader.py
mltrace/log_reader/file_log_reader.py
mltrace/log_reader/log_reader.py
cloud_diagnostics_xprof-0.1.1.dist-info/METADATA
cloud_diagnostics_xprof-0.1.1.dist-info/WHEEL
cloud_diagnostics_xprof-0.1.1.dist-info/entry_points.txt
cloud_diagnostics_xprof-0.1.1.dist-info/top_level.txt
cloud_diagnostics_xprof-0.1.1.dist-info/RECORD
