Metadata-Version: 2.4
Name: cloud-diagnostics-xprof
Version: 0.1.1
Summary: Abstraction over profile session locations and infrastructure running the analysis.
Author-email: Hypercompute Diagon <hypercompute-diagon@google.com>
License: Apache-2.0
Project-URL: Homepage, https://github.com/AI-Hypercomputer/cloud-diagnostics-xprof
Project-URL: Issues, https://github.com/AI-Hypercomputer/cloud-diagnostics-xprof/issues
Classifier: Programming Language :: Python :: 3.8
Classifier: Programming Language :: Python :: 3.9
Classifier: Programming Language :: Python :: 3.10
Classifier: Programming Language :: Python :: 3.11
Classifier: Programming Language :: Python :: 3.12
Requires-Python: >=3.8
License-File: LICENSE
Requires-Dist: tabulate>=0.9.0
Requires-Dist: google-cloud-storage
Requires-Dist: google-auth
Dynamic: license-file
